bearing_new_2/__init__.py
bearing_new_2/bearing.py
bearing_new_2-0.3.dist-info/METADATA
bearing_new_2-0.3.dist-info/WHEEL
bearing_new_2-0.3.dist-info/top_level.txt
bearing_new_2-0.3.dist-info/RECORD
